example/__init__.py
example/app.py
example/events/__init__.py
example/events/ping.py
example/services/__init__.py
example/services/rabbit.py
w_pika/ExchangeParams.py
w_pika/ExchangeType.py
w_pika/QueueParams.py
w_pika/RabbitConsumerMiddleware.py
w_pika/RabbitMQ.py
w_pika/__init__.py
wrapper_pika-0.0.5.dist-info/LICENSE
wrapper_pika-0.0.5.dist-info/METADATA
wrapper_pika-0.0.5.dist-info/WHEEL
wrapper_pika-0.0.5.dist-info/top_level.txt
wrapper_pika-0.0.5.dist-info/RECORD
