Metadata-Version: 2.1
Name: wrapper-pika
Version: 0.0.5
Summary: Adapter for RabbitMQ pika
Home-page: https://github.com/sleepingF0x/wrapper-pika
Author: sleepingF0x
Author-email: agent.999th@gmail.com
License: MIT
Project-URL: Home, https://github.com/sleepingF0x/wrapper-pika
Project-URL: Documentation, https://github.com/sleepingF0x/wrapper-pika/blob/master/README.MD
Project-URL: Issue Tracker, https://github.com/sleepingF0x/wrapper-pika/issues
Project-URL: Source, https://github.com/sleepingF0x/wrapper-pika
Project-URL: Download, https://pypi.org/project/wrapper-pika
Keywords: pika,rabbitmq
Platform: UNKNOWN
Classifier: Development Status :: 3 - Alpha
Classifier: Intended Audience :: Developers
Classifier: Topic :: Software Development :: Build Tools
Classifier: License :: OSI Approved :: MIT License
Classifier: Programming Language :: Python :: 3
Classifier: Programming Language :: Python :: 3.8
Classifier: Programming Language :: Python :: 3.9
Classifier: Programming Language :: Python :: 3.10
Classifier: Programming Language :: Python :: 3.11
Requires-Python: >=3.6
License-File: LICENSE
Requires-Dist: pika >=1.3.2
Requires-Dist: retry >=0.9.2
